{
    "config": {
        "postsPerPage": 18,
        "tagsPostsPerPage": 18,
        "authorsPostsPerPage": 18,
        "excerptLength": 12,
        "logo": "media/website/Logov2whEye.png"
    },
    "customConfig": {
        "pageWidth": "80rem",
        "pageMargin": "4vw",
        "entryWidth": "90ch",
        "frontSource": "post",
        "frontPost": 5,
        "frontGallery": false,
        "layoutFrontpage": "1",
        "layoutTags": "0",
        "layoutAuthor": "0",
        "gridGap": "0.75",
        "relatedPostsNumber": "0",
        "navbarHeight": "4rem",
        "submenu": "auto",
        "submenuWidth": "300",
        "mobilemenu": "sidebar",
        "mobilemenuExpandableSubmenus": true,
        "widthHero": "hero--narrow",
        "heightMinHero": "5rem",
        "heightMaxHero": "25rem",
        "backgroundHero": "#111111",
        "opacityHero": "0",
        "displayHeroImage": true,
        "uploadHero": "media/website/afterlife.jpg",
        "uploadHeroAlt": "",
        "uploadHeroCaption": "",
        "textHero": "<p>Danetron3030</p>",
        "siteOwner": false,
        "lastUpdate": false,
        "cardHeight": "20rem",
        "layoutTypeBorderRadius": "3",
        "cardsOpacity": "0.4",
        "cardsAccentOpacity": "0.95",
        "cardImgScale": "1.6",
        "cardsImgRotate": "-10",
        "cardsDate": true,
        "primaryColor": "#BB2BFF",
        "textColor": "#D9D9D9",
        "headingsColor": "#D5D5D5",
        "fontBody": "petrona",
        "fontHeadings": "metalmania",
        "fontMenu": "var(--heading-font)",
        "fontLogo": "var(--body-font)",
        "minFontSize": "1",
        "maxFontSize": "1.4",
        "lineHeight": "1.4",
        "fontBodyWeight": "305",
        "fontBoldWeight": "648",
        "fontHeadignsWeight": "700",
        "fontHeadingsTransform": "none",
        "shareFacebook": false,
        "shareTwitter": false,
        "shareTwitterName": "",
        "sharePinterest": false,
        "shareMix": false,
        "shareLinkedin": false,
        "shareBuffer": false,
        "shareWhatsApp": false,
        "copyrightText": "<p class=\"align-center\"><img class=\"footer-image\" src=\"/footer.webp\"></p>\n<p class=\"align-center\">Art and lore by <a href=\"https://twitter.com/TheDanetron3030\" target=\"_blank\" rel=\"noopener\">@TheDanetron3030</a></p>\n<p class=\"align-center\">Join us <svg xmlns=\"http://www.w3.org/2000/svg\" width=\"16\" height=\"16\" fill=\"currentColor\" class=\"bi bi-arrow-down\" viewbox=\"0 0 16 16\"> <path fill-rule=\"evenodd\" d=\"M8 1a.5.5 0 0 1 .5.5v11.793l3.146-3.147a.5.5 0 0 1 .708.708l-4 4a.5.5 0 0 1-.708 0l-4-4a.5.5 0 0 1 .708-.708L7.5 13.293V1.5A.5.5 0 0 1 8 1z\"></path> </svg></p>",
        "socialButtons": true,
        "socialFacebook": "",
        "socialTwitter": "https://twitter.com/TheDanetron3030",
        "socialDiscord": "https://discord.gg/danetrons-afterlife",
        "socialInstagram": "",
        "socialLinkedin": "",
        "socialVimeo": "",
        "socialPinterest": "",
        "socialYoutube": "",
        "searchFeature": false,
        "createSearchPage": false,
        "galleryItemGap": "0.5rem",
        "galleryLightboxStyle": "pswp--dark",
        "galleryLightboxOpacity": "0.7",
        "galleryAdvanced": false,
        "galleryCounter": true,
        "galleryZoom": true,
        "galleryFullscreen": true,
        "galleryShare": true,
        "galleryClose": true,
        "galleryArrows": true,
        "galleryPreloader": true,
        "galleryCloseOnScroll": true,
        "galleryArrowKeys": true,
        "backToTopButton": true,
        "formatDate": "MMMM D, YYYY",
        "formatDateCustom": "HH:mm:ss YY/MM/DD",
        "lazyLoadEffect": "fadein",
        "faviconUpload": "media/website/favicon.ico",
        "faviconExtension": "image/x-icon"
    },
    "postConfig": {
        "displayCategoryName": "0",
        "displayAuthor": "0",
        "displayDate": "0",
        "displayLastUpdatedDate": "0",
        "displayShareButtons": "0",
        "displayTags": "0",
        "displayAuthorBio": "0",
        "displayPostNavigation": "0",
        "displayRelatedPosts": "0",
        "displayComments": 0
    },
    "tagConfig": {},
    "authorConfig": {},
    "defaultTemplates": {
        "post": ""
    }
}